wslink/LICENSE
wslink/__init__.py
wslink/chunking.py
wslink/emitter.py
wslink/launcher.py
wslink/protocol.py
wslink/publish.py
wslink/relay.py
wslink/server.py
wslink/ssl_context.py
wslink/uri.py
wslink/websocket.py
wslink/backends/__init__.py
wslink/backends/aiohttp/__init__.py
wslink/backends/aiohttp/launcher.py
wslink/backends/aiohttp/relay.py
wslink/backends/generic/__init__.py
wslink/backends/generic/core.py
wslink/backends/jupyter/__init__.py
wslink/backends/jupyter/core.py
wslink/backends/tornado/__init__.py
wslink/backends/tornado/core.py
wslink-2.3.2.dist-info/METADATA
wslink-2.3.2.dist-info/WHEEL
wslink-2.3.2.dist-info/top_level.txt
wslink-2.3.2.dist-info/RECORD
