Metadata-Version: 2.1
Name: wslink
Version: 2.3.2
Summary: Python/JavaScript library for communicating over WebSocket
Home-page: https://github.com/kitware/wslink
Author: Kitware, Inc.
Author-email: kitware@kitware.com
License: BSD-3-Clause
Keywords: websocket javascript rpc pubsub
Classifier: Development Status :: 5 - Production/Stable
Classifier: Environment :: Web Environment
Classifier: License :: OSI Approved :: BSD License
Classifier: Operating System :: OS Independent
Classifier: Programming Language :: Python
Classifier: Programming Language :: Python :: 3
Classifier: Programming Language :: Python :: 3.3
Classifier: Programming Language :: Python :: 3.4
Classifier: Programming Language :: Python :: 3.5
Classifier: Programming Language :: Python :: 3.6
Classifier: Programming Language :: Python :: 3.7
Classifier: Programming Language :: Python :: 3.8
Classifier: Programming Language :: Python :: 3.9
Classifier: Topic :: Software Development :: Libraries :: Python Modules
Requires-Dist: aiohttp<4
Requires-Dist: msgpack<2,>=1
Provides-Extra: ssl
Requires-Dist: cryptography; extra == "ssl"
